LICENSE
MANIFEST.in
README.rst
setup.py
supertools/__init__.py
supertools.egg-info/PKG-INFO
supertools.egg-info/SOURCES.txt
supertools.egg-info/dependency_links.txt
supertools.egg-info/top_level.txt