Metadata-Version: 1.0
Name: supertools
Version: 1.0.1
Summary: A simple python module to provide .__super ability to python 2 classes.
Home-page: https://github.com/gissehel/supertools.git
Author: Arthibus Gisséhel
Author-email: public-dev-supertools@gissehel.org
License: MIT
Keywords: super supertools superable
Platform: UNKNOWN
Classifier: Development Status :: 5 - Production/Stable
Classifier: Intended Audience :: Developers
Classifier: License :: OSI Approved :: MIT License
Classifier: Programming Language :: Python :: 2
Classifier: Programming Language :: Python :: 2 :: Only
